[
  {
    "name": "Lawenda",
    "type": "ozdobna",
    "pruning": {
      "main": { "start": "08-20", "end": "09-15" },
      "secondary": { "start": "04-01", "end": "04-20" }
    },
    "instructions": [
      "Nie tnij w stare, zdrewniałe czesci – lawenda nie odrasta ze starego drewna.",
      "Tnij bezposrednio po przekwitnieciu (sierpien–wrzesien), skracajac wszystkie przekwitłe pedy kwiatowe.",
      "Nadaj krzewowi ksztalt zwartej kopuly, zostawiajac 2–3 cm zielonych pedow nad zdrewniała czescia.",
      "Wiosenne ciecie (kwiecien): usun przemarzniete koncowki i delikatnie uformuj krzew po zimie.",
      "Uzywaj ostrych, odkazonych nozyczek – zranione pedy sa wrotami dla chorob grzybowych.",
      "Posypanie ziemi wokol krzewu piaskiem lub zwirem poprawia wentylacje i zmniejsza ryzyko gniciai."
    ]
  },
  {
    "name": "Róża rabatowa",
    "type": "ozdobna",
    "pruning": {
      "main": { "start": "03-15", "end": "04-10" }
    },
    "instructions": [
      "Tnij wczesna wiosna, gdy pakiety forsycji zaczynaja pekac – to tradycyjny sygnał termiczny.",
      "Usuń wszystkie martwe, chore i cienkie pedy (ciensze niz olowek) przy nasadzie.",
      "Skroc zdrowe pedy do 3–5 oczek (ok. 15–25 cm od ziemi), dla duzych kwiatow ciniej nizej.",
      "Wytnij pedy krzyzujace sie i rosnace do srodka krzewu, by zapewnic dobra wentylacje.",
      "Kazde ciecie wykonuj pod katem 45 stopni, ok. 5 mm nad skierowanym na zewnatrz pakiem.",
      "Odkaz narzedzia miedzy kazdym krzewem spirytusem lub preparatem do odkadzania narzedzi."
    ]
  },
  {
    "name": "Róża pnąca",
    "type": "ozdobna",
    "pruning": {
      "main": { "start": "03-20", "end": "04-15" }
    },
    "instructions": [
      "Usuń stare, wieloletnie pedy przy ziemi – roze pnace kwitna na mlodym drewnie biezacego roku.",
      "Pozostaw 3–5 najsilniejszych, mlodych pedow i zwiaz je do konstrukcji.",
      "Przywiaz pedy poziomo lub w luku (nie pionowo) – to stymuluje kwitnienie na całej dlugosci.",
      "Skroc boczne rozgalezienia (pedy kwiatowe) do 2–4 oczek od głównego peda.",
      "Usuń pedy martwe, chore i krzyzujace sie.",
      "Po kwitnieniu regularnie usuwaj przekwitłe kwiatostany, by pobudzic powtorne kwitnienie."
    ]
  },
  {
    "name": "Hortensja bukietowa",
    "type": "ozdobna",
    "pruning": {
      "main": { "start": "02-15", "end": "03-20" }
    },
    "instructions": [
      "Kwitnie na nowym drewnie – ciecie wiosna pobudza obfite kwitnienie w tym samym roku.",
      "Skroc wszystkie ubiegłoroczne pedy o 1/3 do 1/2 dlugosci ponad zdrowy pak.",
      "Całkowicie usuń pedy slabe, cienkie i krzyzujace sie.",
      "Silniejsze ciecie = mniej, ale wiekszych kwiatostanow; słabsze = wiecej, mniejszych.",
      "Stare, brązowe kwiatostany pozostaw przez zime – chronia paki przed mrozem, usun je dopiero przy cieciu wiosennym.",
      "Nie tnij jesienia – swiezo przyciete pedy moga przemarzac."
    ]
  },
  {
    "name": "Hortensja ogrodowa",
    "type": "ozdobna",
    "pruning": {
      "secondary": { "start": "06-20", "end": "07-20" }
    },
    "instructions": [
      "Kwitnie na starym drewnie – paki kwiatowe tworzą sie jesienia poprzedniego roku, nie tnij mocno.",
      "Usuń wyłacznie przekwitłe kwiatostany, tujac tuz nad pierwsza para zdrowych pakow.",
      "Stare kwiatostany pozostaw przez zime – chronią paki kwiatowe przed mrozem.",
      "Wiosna (marzec–kwiecien) przytnij delikatnie koncowki przemarzłych pedow do zywego drewna.",
      "Raz na kilka lat usuń przy ziemi 1–2 najstarsze pedy, by odmłodzic krzew.",
      "Unikaj cięcia kształtujacego – niszczy paki kwiatowe na przyszły rok."
    ]
  },
  {
    "name": "Budleja Dawida",
    "type": "ozdobna",
    "pruning": {
      "main": { "start": "03-01", "end": "03-25" }
    },
    "instructions": [
      "Kwitnie na pedach biezacego roku – wiosenne mocne ciecie jest obowiazkowe dla obfitego kwitnienia.",
      "Przytnij wszystkie ubiegłoroczne pedy do 30–40 cm od ziemi (do 2–3 par pakow).",
      "Calkowicie usuń pedy słabe, cienkie i przemarzniete.",
      "Mozna rowniec scinac mocniej – do 15–20 cm od ziemi – roślina odbuduje sie z korzeni.",
      "Jesienia (pazdziernik) mozesz skrocic pedy o 1/3, by wiatr nie kiwał krzewem i nie uszkodzil korzeni.",
      "Bardzo szybko rosnaca roslina – po mocnym cieciu wiosna wypuszcza nowe pedy do 2 m dlugosci."
    ]
  },
  {
    "name": "Forsycja",
    "type": "ozdobna",
    "pruning": {
      "main": { "start": "04-10", "end": "05-10" }
    },
    "instructions": [
      "Kwitnie na starym drewnie – tnij WYŁACZNIE bezposrednio po kwitnieniu (kwiecien–maj), nigdy jesienia ani zima.",
      "Zaraz po przekwitnieciu usuń przy ziemi 1/3 najstarszych pedow (ciemnobrązowe, grube).",
      "Pozostale pedy skroc o 1/3, nadajac krzewowi regularny ksztalt.",
      "Unikaj ciecai w sierpniu, wrzesniu i pazdzierniku – usuniesz paki kwiatowe zawiazane na lato i na przyszly rok.",
      "Co kilka lat odmłodz cały krzew przez silne sciecie prawie wszystkich pedow przy ziemi zaraz po kwitnieniu.",
      "Dobrze przycieta forsycja kwitnie obficiej – zbyt duzy krzew bez cięcia z wiekiem kwitnie słabiej."
    ]
  },
  {
    "name": "Jaśminowiec",
    "type": "ozdobna",
    "pruning": {
      "main": { "start": "06-15", "end": "07-10" }
    },
    "instructions": [
      "Kwitnie na ubiegłorocznych pedach – tnij ZARAZ po kwitnieniu (czerwiec–lipiec).",
      "Wytnij przy ziemi 1/3 najstarszych, najciemniejszych pedow (korkowate, grube).",
      "Skroc o 1/3 pozostałe pedy, ktore juz przekwitły.",
      "Usuń pedy słabe, krzyzujace sie i rosnace do srodka krzewu.",
      "Nie tnij w sierpniu, wrzesniu ani pozniej – na nowych pedach juz tworza sie paki kwiatowe na przyszly rok.",
      "Co kilka lat mozesz wykonac silne odmładzanie, scinajac prawie wszystkie pedy przy ziemi."
    ]
  },
  {
    "name": "Tawuła japońska",
    "type": "ozdobna",
    "pruning": {
      "main": { "start": "03-01", "end": "03-30" }
    },
    "instructions": [
      "Kwitnie latem na pedach biezacego roku – wiosenne ciecie jest konieczne dla obfitego kwitnienia.",
      "Skroc wszystkie pedy mocno, do 15–20 cm od ziemi (lub o 2/3 dlugosci).",
      "Całkowicie usuń pedy słabe, cienkie i uszkodzone przez mroz.",
      "Mocne ciecie wymusza silny wzrost i obfite letnie kwitnienie (czerwiec–sierpien).",
      "Po pierwszym kwitnieniu mozesz lekko przyciać przekwitłe pedy, by pobudzic powtorne kwitnienie.",
      "Regeneruje sie bardzo szybko – nie obawiaj sie mocnego cięcia wiosna."
    ]
  },
  {
    "name": "Tawuła wczesna",
    "type": "ozdobna",
    "pruning": {
      "main": { "start": "05-01", "end": "06-01" }
    },
    "instructions": [
      "Kwitnie wiosna na starych pedach (ubiegłorocznych) – tnij WYŁACZNIE bezposrednio po kwitnieniu.",
      "Usuń przekwitłe pedy, skracajac je do widocznego, silnego nowego przyrostu.",
      "Co roku wytnij przy ziemi 1–2 najstarsze pedy, by stopniowo odmładzac krzew.",
      "Unikaj cięcia pozniejszego niz lipiec – usuniesz paki kwiatowe na przyszły rok.",
      "Regularnie przeswietlaj srodek krzewu dla dobrego przepływu powietrza.",
      "Nie tnij mocno wiosna przed kwitnieniem – stracisz cały sezon kwitnienia."
    ]
  },
  {
    "name": "Berberys",
    "type": "ozdobna",
    "pruning": {
      "main": { "start": "03-15", "end": "04-15" }
    },
    "instructions": [
      "Zakładaj grube rekawice skorzane – kolce berberysu sa ostre i łatwo wnikaja w skore.",
      "Tnij wczesna wiosna (marzec–kwiecien) przed pelnym rozwojem lisci lub po kwitnieniu.",
      "Formuj krzew, nadajac mu pozadany ksztalt (kulisty, naturalny lub zywoplot).",
      "Usuń pedy rosnace do srodka krzewu, wiotkie, chore i uszkodzone mrozem.",
      "W zywopłocie przycinaj 2 razy w sezonie (maj i sierpien) dla gestego i rownego efektu.",
      "Odrosty korzeniowe wyrywaj lub scinaj przy ziemi, by nie oslabiac głownego krzewu."
    ]
  },
  {
    "name": "Ligustr",
    "type": "ozdobna",
    "pruning": {
      "main": { "start": "05-01", "end": "08-20" }
    },
    "instructions": [
      "Wymaga regularnego cięcia przez cały sezon wegetacyjny dla gestego efektu zywopłotu.",
      "Pierwsze ciecie: maj–czerwiec, po zakończeniu intensywnego wzrostu wiosennego.",
      "Drugie ciecie: sierpien, by zachowac ksztalt i zageszczenie przed zima.",
      "Przycinaj gore zywopłotu wezej niz dol – dolne galazki beda mialy dostep do swiatła.",
      "Uzywaj nozyczek do zywopłotu (recznych lub elektrycznych) dla rownego, czystego efektu.",
      "Unikaj ciecai po połowie wrzesnia – nowe pedy nie zdaza stwardniec przed mrozem."
    ]
  },
  {
    "name": "Żywotnik (tuja)",
    "type": "ozdobna",
    "pruning": {
      "main": { "start": "05-01", "end": "08-15" }
    },
    "instructions": [
      "NIE tnij w stare, brązowe drewno bez igieł – tuja nie odrasta ze starego drewna.",
      "Tnij wyłacznie zielone, tegoroczne i ubiegłoroczne przyrosty.",
      "Pierwsze ciecie: maj–czerwiec, po gównym wzroscie wiosennym.",
      "Drugie ciecie: sierpien–połowa wrzesnia; nie tnij pozniej – nowe pedy moga przemarzac.",
      "Formuj regularnie cała bryle krzewu, nie tnij jednostronnie ani asymetrycznie.",
      "Uschnięte galazki wewnatrz to normalna fizjologia – usun je delikatnie, by poprawic wentylacje."
    ]
  },
  {
    "name": "Cis",
    "type": "ozdobna",
    "pruning": {
      "main": { "start": "04-01", "end": "09-01" }
    },
    "instructions": [
      "Doskonale znosi ciecie nawet w stare drewno – odrasta ze starych pni i konarow.",
      "Formuj 2–3 razy w sezonie: kwiecien, lipiec i koniec sierpnia dla gestej bryły.",
      "Tnij w dowolny ksztalt (stozek, kula, szpaler, topiaria) – cis jest idealny do form.",
      "Unikaj cięcia po połowie wrzesnia – nowe pedy nie zdaza stwardniec przed mrozem.",
      "Pamietaj: tuja NIE znosi cięcia w stare drewno; cis – jak najbardziej znosi.",
      "UWAGA: wszystkie czesci cisa sa silnie trujace – myj rece po pracy i nie kompustuj odpadow."
    ]
  },
  {
    "name": "Krzewuszka",
    "type": "ozdobna",
    "pruning": {
      "main": { "start": "06-20", "end": "07-20" }
    },
    "instructions": [
      "Kwitnie na pedach ubiegłorocznych – tnij ZARAZ po kwitnieniu (czerwiec–lipiec).",
      "Usuń przy ziemi 1/4–1/3 najstarszych, najgrubszych pedow.",
      "Skroc pozostale pedy o 1/3, zwłaszcza te, ktore juz przekwitly.",
      "Nie tnij jesienia ani zima – usuwasz paki kwiatowe tworzone na nowych pedach.",
      "Regularnie przeswietlaj krzew, by srodek mial dostep do swiatła i powietrza.",
      "Co roku odnawiaj krzew – zastepuj stare pedy mlodymi dla obfitego kwitnienia."
    ]
  },
  {
    "name": "Pięciornik krzewiasty",
    "type": "ozdobna",
    "pruning": {
      "main": { "start": "03-01", "end": "03-30" }
    },
    "instructions": [
      "Kwitnie przez całe lato (czerwiec–wrzesien) na pedach biezacego roku – tnij wiosna.",
      "Skroc wszystkie pedy o 1/3 do 1/2 dlugosci nad zdrowym pakiem.",
      "Całkowicie usuń pedy martwe, uszkodzone mrozem i wyjatkowo cienkie.",
      "Jest bardzo odporny i regeneruje sie szybko – nie obawiaj sie cięcia.",
      "Jesienia mozesz lekko skrocic pedy, by krzew był bardziej zwarty przez zime.",
      "Kwitnie bez przerwy przez całe lato – regularne usuwanie przekwitłych kwiatow nie jest konieczne."
    ]
  },
  {
    "name": "Perukowiec",
    "type": "ozdobna",
    "pruning": {
      "main": { "start": "03-01", "end": "03-25" }
    },
    "instructions": [
      "Kwitnie na pedach biezacego roku; mocne ciecie wiosna zapewnia najlepszy kolor lisci.",
      "Silne ciecie (do 30–50 cm) wymusza wzrost mlodych pedow z intensywnie wybarwionymi, fioletowymi liscmi.",
      "Usuń cienkie, słabe pedy przy nasadzie krzewu.",
      "Minimaliste ciecie (tylko sanitarne) = wieksze drzewo z naturalna sylwetka, mniej intensywny kolor.",
      "Perukowiec po cieciu moze 'krwawic' (wydziela sok) – to normalne; nie wymaga zabezpieczenia.",
      "Jesienia nie tnij – pedy powinny stwardniec przed zima, by dobrze prezrezimowac."
    ]
  },
  {
    "name": "Trzmielina",
    "type": "ozdobna",
    "pruning": {
      "main": { "start": "04-01", "end": "08-01" }
    },
    "instructions": [
      "Tnij wiosna (kwiecien–maj) przed pelnym rozwojem lisci lub po kwitnieniu.",
      "Formuj dowolnie – jako zywoplot, szpaler lub wolno rosnacy krzew.",
      "Usuń pedy rosnace nieregularnie, uszkodzone mrozem i krzyzujace sie.",
      "Odrosty korzeniowe wycinaj regularnie – trzmielina silnie odrosla poza pożadany obszar.",
      "W zywopłocie przycinaj 2 razy w sezonie (maj i sierpien) dla gestego efektu.",
      "UWAGA: owoce trzmieliny sa trujace (szczegolnie dla dzieci i zwierzat) – pamietaj o tym w ogrodzie."
    ]
  },
  {
    "name": "Jałowiec",
    "type": "ozdobna",
    "pruning": {
      "main": { "start": "04-01", "end": "06-01" }
    },
    "instructions": [
      "Tnij WYŁACZNIE zielone, tegoroczne przyrosty – stare drewno bez igieł nie odrasta.",
      "Najlepszy termin: kwiecien–maj lub bezposrednio po wzroscie wiosennym (czerwiec).",
      "Usuń suche, brązowe galazki wewnatrz korony – to normalna fizjologia, nie choroba.",
      "Formuj delikatnie, skracajac tylko koncowki pedow – nie tnij agresywnie.",
      "Unikaj intensywnego cięcia jednorazowego – wykonuj je stopniowo przez kilka sezonow.",
      "Jalowce poziome wymagaja mniej cięcia niz kolumnowe – formuj tylko w razie potrzeby."
    ]
  },
  {
    "name": "Jabłoń",
    "type": "owocowa",
    "pruning": {
      "main": { "start": "02-10", "end": "03-20" },
      "summer": { "start": "07-10", "end": "07-30" }
    },
    "instructions": [
      "Glowne ciecie: koniec zimy (luty–marzec) przed pecznieniem pakow – drzewo widac, rana szybko sie goi.",
      "Usuń wilki (pionowe, bezowocne pedy rosnace stromo w gore) – pobieraja wode i skladniki odżywcze.",
      "Przeswietl korone, usuwajac pedy krzyzujace sie i zagęszczajace – swiatlo = lepsza jakosc owocow.",
      "Skroc pedy jednoroczne o 1/3 nad pakiem skierowanym na zewnatrz korony.",
      "Letnie ciecie (lipiec): usuń zbedne pedy zielone, by poprawic jakość owocow i ograniczyc choroby.",
      "Stare, zaniedbane drzewa odmładzaj stopniowo przez 3–4 lata, nie jednorazowo – nagły szok osłabia drzewo."
    ],
    "harvest": {
      "start": "08-20",
      "end": "10-15",
      "appearance": "Owoce maja pełne zabarwienie charakterystyczne dla odmiany (czerwone, żolte lub zielone). Daja sie łatwo obrywac po delikatnym przekreceniu. Skórka twarda, miązsz soczysty i chrupiacy."
    }
  },
  {
    "name": "Grusza",
    "type": "owocowa",
    "pruning": {
      "main": { "start": "02-10", "end": "03-20" }
    },
    "instructions": [
      "Glowne ciecie: koniec zimy (luty–marzec) przed pecznieniem pakow.",
      "Usuń pedy rosnace do srodka korony i pionowe bezowocne pedy (wilki).",
      "Przeswietl korone – grusza wymaga dobrego dostepu swiatła dla jakosci owocow.",
      "Skroc pedy jednoroczne o 1/3 nad pakiem skierowanym na zewnatrz korony.",
      "Unikaj mocnego cięcia – grusza reaguje gwałtownym wzrostem wilkow po silnym cieciu.",
      "Starsze drzewa – utrzymuj stała wysokosc i ksztalt, usuwaj tylko to, co niezbedne."
    ],
    "harvest": {
      "start": "08-01",
      "end": "10-15",
      "appearance": "Skórka żółknie lub brunatnieje zaleznie od odmiany. Owoc lekko ustepuje pod palcem przy szypułce. Wiele odmian zbiera sie nieco przed pełna dojrzałoscia i dosypia w chłodnym miejscu."
    }
  },
  {
    "name": "Śliwa",
    "type": "owocowa",
    "pruning": {
      "main": { "start": "08-01", "end": "09-10" }
    },
    "instructions": [
      "TNIJ WYŁACZNIE LATEM (sierpien–wrzesien), po zbiorach – zimowe i wiosenne ciecie grozi srebrzystoscia lisci.",
      "Usuń chore, martwe i uszkodzone pedy niezwłocznie po wykryciu przez cały sezon.",
      "Przeswietl korone, usuwajac pedy rosnace do srodka i krzyzujace sie.",
      "Skroc zbyt dlugie pedy o 1/3, ciecie wykonuj ostrzem nad zdrowym pakiem.",
      "Rany po cieciu natychmiast smaruj mascia ogrodowa lub Funabenem – sliwy sa bardzo podatne na infekcje.",
      "Unikaj duzych, jednorazowych ciec – gorzej regeneruja sie niz jabłonie i grusze."
    ],
    "harvest": {
      "start": "07-15",
      "end": "09-15",
      "appearance": "Owoce maja intensywny kolor wlasciwy dla odmiany (fioletowy, żolty lub czerwony), pokryte woskowatym nalotem (siną oproszka). Lekko miekkie pod dotykiem, słodkie i aromatyczne."
    }
  },
  {
    "name": "Wiśnia",
    "type": "owocowa",
    "pruning": {
      "main": { "start": "07-15", "end": "08-20" }
    },
    "instructions": [
      "TNIJ WYŁACZNIE PO ZBIORACH (lipiec–sierpien) – zimowe ciecie naraża na srebrzystosc lisci i inne choroby.",
      "Usuń pedy krzyzujace sie i rosnace do srodka korony.",
      "Skroc zbyt dlugie pedy jednoroczne, zostawiajac 40–50 cm od punktu odgałezienia.",
      "Rany powyzej 2 cm srednicy natychmiast zabezpiecz mascia ogrodowa.",
      "Unikaj silnego cięcia ksztaltujacego – wisnia zle toleruje drastyczne interwencje.",
      "Odrosty korzeniowe wycinaj na biezaco – wyrastaja z podkładki i moga zdominowac drzewo."
    ],
    "harvest": {
      "start": "06-10",
      "end": "07-20",
      "appearance": "Ciemnoczerwone lub prawie czarne, błyszczace owoce z zielona, elastyczna szypułka. Pełne, soczyste i kwaśno-słodkie. Zrywamy całe grona."
    }
  },
  {
    "name": "Czereśnia",
    "type": "owocowa",
    "pruning": {
      "main": { "start": "07-20", "end": "08-25" }
    },
    "instructions": [
      "TNIJ WYŁACZNIE LATEM (lipiec–sierpien), bezposrednio po zbiorach – zimowe ciecie jest bardzo szkodliwe.",
      "Ogranicz ciecie do minimum – czeresnia jest wrazliwa na ciecie i wolno sie regeneruje.",
      "Usuń chore i martwe pedy niezwłocznie po wykryciu.",
      "Przeswietl korone delikatnie – nie usuwaj wiecej niz 1/4 korony jednorazowo.",
      "Rany powyzej 2 cm srednicy natychmiast zabezpiecz preparatem ogrodowym (mascia lub Funabenem).",
      "Nie prob kształtowac mocno duzych drzew – ryzyko chorob jest za wysokie."
    ],
    "harvest": {
      "start": "06-01",
      "end": "07-15",
      "appearance": "Ciemnoczerwone lub żołto-czerwone owoce z błyszczaca skorka. Twarde i soczyste, łatwo odrywaja sie od szypułki. Im ciemniejsze zabarwienie, tym słodsze."
    }
  },
  {
    "name": "Brzoskwinia",
    "type": "owocowa",
    "pruning": {
      "main": { "start": "03-01", "end": "03-25" }
    },
    "instructions": [
      "Kwitnie i owocuje na pedach jednorocznych – ciecie wiosna (marzec) przed kwitnieniem jest kluczowe.",
      "Formuj korone na ksztalt otwartego wazonu: usuń pedy rosnace do srodka i stromo pionowo.",
      "Skroc pedy owocujace o połowe – zbyt intensywne owocowanie wyczerpuje drzewo.",
      "Usuń pedy z objawami kedziersawosci lisci (brązowe, zdeformowane paki – juz po zimie).",
      "Rany zabezpiecz mascia ogrodowa – brzoskwinia jest podatna na monilioze i inne choroby grzybowe.",
      "Po ewentualnych poznych przymrozkach sprawdz pak kwiatowe – podetnij tylko jesli widac uszkodzenia."
    ],
    "harvest": {
      "start": "07-01",
      "end": "09-01",
      "appearance": "Żolto-pomaranczowe lub czerwonawe zabarwienie, skórka pokryta delikatnym puchem. Lekko miekkie przy szypułce, intensywnie aromatyczne. Zrywamy ostroznie, trzymajac za owoc, nie ciagnac za szypułke."
    }
  },
  {
    "name": "Morela",
    "type": "owocowa",
    "pruning": {
      "main": { "start": "04-01", "end": "04-30" }
    },
    "instructions": [
      "Tnij po ostatnich przymrozkach (kwiecien) – morela kwitnie bardzo wczesnie i jest podatna na uszkodzenia mrozem.",
      "Usuń gałęzie chore (srebrzystosc lisci, dziurkowatość lisci), martwe i uszkodzone mrozem.",
      "Przeswietl korone – morela owocuje na starszym drewnie (2–5-letnich pedach).",
      "Zachowaj naturalna sylwetke drzewa (piramida lub otwarty wazon); nie tnij mocno.",
      "Rany smaruj mascia ogrodowa – morela jest podatna na choroby grzybowe i bakteryjne.",
      "Zbyt częste i mocne ciecia osłabic drzewo – lepiej mało i regularnie niz rzadko i agresywnie."
    ],
    "harvest": {
      "start": "07-01",
      "end": "08-15",
      "appearance": "Pomaranczowe lub żolto-pomaranczowe owoce, lekko miekkie w dotyku, aromatyczne. Pestka łatwo oddziela sie od miązszu. Dojrzałe opadaja same lub zrywaja sie bez oporu."
    }
  },
  {
    "name": "Porzeczka czarna",
    "type": "owocowa",
    "pruning": {
      "main": { "start": "02-01", "end": "03-10" }
    },
    "instructions": [
      "Owocuje głownie na pedach 1–2-letnich – starsze pedy sa mało produktywne.",
      "Co roku usuń przy ziemi wszystkie pedy starsze niz 3–4 lata (ciemnobrązowe, korkowate).",
      "Zostaw 4–6 najsilniejszych pedow jednorocznych i dwuletnich.",
      "Wiosna skroc pedy zbyt dlugie lub rosnace po ziemi.",
      "Po 5 latach mozna radykalnie odmłodzic krzew, scinajac wszystko przy ziemi.",
      "Stare pedy łatwo rozpoznac: ciemnobrązowe lub czarne, grube i zdrewniałe = do usuniecia."
    ],
    "harvest": {
      "start": "07-01",
      "end": "08-10",
      "appearance": "Czarne, matowe jagody w gronach – wszystkie powinny byc jednolicie ciemne. Grona zrywamy w całosci, gdy ostatnia jagoda dojrzeje. Słodko-kwasny, intensywny smak i aromat."
    }
  },
  {
    "name": "Porzeczka czerwona",
    "type": "owocowa",
    "pruning": {
      "main": { "start": "02-01", "end": "03-10" }
    },
    "instructions": [
      "Owocuje na starszym drewnie (2–5-letnich pedach) – nie usuwaj wszystkich starszych pedow.",
      "Co roku wytnij przy ziemi tylko najstarsze pedy (powyzej 5 lat, ciemnoszare, mało produktywne).",
      "Zostaw szkielet 8–10 pedow rożnego wieku (mlodsze i starsze razem).",
      "Usuń odrosty z ziemi rosnace poza obszarem krzewu.",
      "Przeswietl srodek krzewu, by poprawic wentylacje i zmniejszyc ryzyko choroby grzybowych.",
      "Krzew mozesz formowac jako wielopedowy krzew lub jako pien na sztopionce (porzeczka na pieniu)."
    ],
    "harvest": {
      "start": "07-01",
      "end": "08-01",
      "appearance": "Jasnoczerwone, przezroczyste i błyszczace jagody w zwisajacych gronach. Zrywamy całe grona, gdy wszystkie jagody sa w pełni wybarwione. Kwasny, ozezwiajacy smak."
    }
  },
  {
    "name": "Agrest",
    "type": "owocowa",
    "pruning": {
      "main": { "start": "02-01", "end": "03-10" }
    },
    "instructions": [
      "Zakładaj grube rekawice skorzane – agrest ma dlugie, ostre kolce.",
      "Co roku usuń pedy krzyzujace sie w srodku krzewu i rosnace poziomo przy ziemi.",
      "Zostaw otwarta 'mise' w srodku krzewu – dobra wentylacja chroni przed maczniakiem agrestowym.",
      "Usuń pedy starsze niz 4 lata (mało produktywne, ciemnobrązowe).",
      "Regularnie usuwaj odrosty korzeniowe rosnace poza obszarem krzewu.",
      "Wiosna skroc pedy jednoroczne o 1/3, zostawiajac 3–4 paki od nasady."
    ],
    "harvest": {
      "start": "06-15",
      "end": "08-15",
      "appearance": "Do przetworow: twarde, zielone jagody zrywamy wczesniej (czerwiec). Do jedzenia: owoce w pełni wybarwione (zielone, żolte lub czerwone zalezenie od odmiany), lekko miekkie i słodkie."
    }
  },
  {
    "name": "Malina letnia",
    "type": "owocowa",
    "pruning": {
      "main": { "start": "08-01", "end": "09-01" }
    },
    "instructions": [
      "Po zbiorach (sierpien) wytnij przy ziemi WSZYSTKIE pedy, ktore owocowały (brązowe, drewniane, 2-letnie).",
      "Zostaw 5–7 najsilniejszych, zielonych pedow jednorocznych na kazdy metr rzędu.",
      "Skroc pozostawione pedy do ok. 150–170 cm lub do pierwszego zdrowego paka.",
      "Usuń wszystkie słabe, cienkie pedy jednoroczne – i tak da słabe owocowanie.",
      "Nowe pedy przywiaz do drutu lub podpory przed zima, by wiatr ich nie złamał.",
      "Wiosna usuń ewentualnie przemarzniete koncowki pozostawionych pedow (do pierwszego żywego paka)."
    ],
    "harvest": {
      "start": "07-01",
      "end": "08-15",
      "appearance": "Ciemnoczerwone owoce, ktore bez wysilku odchodza od szypułki (pestki). Miekkie, aromatyczne, błyszczace. Zbieramy codziennie lub co dwa dni, bo szybko przejrzewaja."
    }
  },
  {
    "name": "Malina powtarzająca",
    "type": "owocowa",
    "pruning": {
      "main": { "start": "10-01", "end": "11-10" }
    },
    "instructions": [
      "Najprostsza metoda: po sezonie (pazdziernik–listopad) sciąc WSZYSTKIE pedy przy ziemi.",
      "Wiosna wyrosna zupelnie nowe pedy, ktore owocuja jesienia (sierpien–pazdziernik) na szczytach.",
      "Metoda na 2 zbiory: zostaw najsilniejsze pedy na wiosenny zbiór w przyszłym roku, usuń po nim.",
      "Tnij tuz nad ziemia, nie zostawiaj kikutow – to siedlisko chorob i szkodnikow.",
      "Stare pedy łatwo rozpoznac: brązowe, zdrewniałe, z bocznymi rozgałezieniami.",
      "Metoda 'scinaj wszystko do ziemi' jest prostsza i daje obfity jesienny zbiór na pędach biezacego roku."
    ],
    "harvest": {
      "start": "09-01",
      "end": "10-20",
      "appearance": "Ciemnoczerwone owoce na szczytach pedow jednorocznych. Odchodza od pestki bez oporu, soczyste i aromatyczne. Drugi zbior w roku – owoce czesto smaczniejsze niz letnie."
    }
  },
  {
    "name": "Jeżyna",
    "type": "owocowa",
    "pruning": {
      "main": { "start": "08-15", "end": "09-20" }
    },
    "instructions": [
      "Kwitnie i owocuje na pedach dwuletnich – po zbiorach wytnij je przy ziemi.",
      "Po zbiorach (sierpien–wrzesien) usuń wszystkie pedy 2-letnie (brązowe, ktore owocowały).",
      "Zostaw 4–6 najsilniejszych pedow jednorocznych (zielone lub czerwonawe) i przywiaz je do podpory.",
      "Wiosna skroc koncowki pedow jednorocznych o ok. 30 cm – pobudza rozgalezienie i owocowanie.",
      "Jezyny bez kolcow wymagaja takiego samego cięcia, lecz praca jest duzo łatwiejsza.",
      "Nie zostawiaj starych pedow – sa siedliskiem chorob grzybowych i szkodnikow."
    ],
    "harvest": {
      "start": "07-20",
      "end": "09-15",
      "appearance": "Głeboko czarne, lsniace owoce – wszystkie kosteczki jednolicie ciemne. Lekko miekkie w dotyku, słodkie. Zrywamy łatwo bez zadnego oporu. Niedojrzale sa czerwone lub fioletowe – zostawiamy je."
    }
  },
  {
    "name": "Borówka wysoka",
    "type": "owocowa",
    "pruning": {
      "main": { "start": "02-15", "end": "03-20" }
    },
    "instructions": [
      "Przez pierwsze 3 lata po posadzeniu nie tnij – pozwol krzewowi sie rozrosnac.",
      "Od 4. roku: co roku usuń najstarsze, najgrubsze pedy (powyzej 6 lat) przy ziemi.",
      "Zostaw 6–8 silnych, zdrowych pedow rożnego wieku (mlodsze i starsze razem).",
      "Usuń drobne, słabe pedy przy podstawie i gałazki z chorymi pakami.",
      "Skroc pedy zbyt długie – borówka owocuje lepiej na gałazkach krotszych niz 50 cm.",
      "WAZNE: gleba musi byc mocno kwaśna (pH 4,0–5,0) – brak cięcia nie pomoze przy złym odczynie."
    ],
    "harvest": {
      "start": "07-01",
      "end": "09-01",
      "appearance": "Niebiesko-sine jagody pokryte woskowym nalotem (pruina), z charakterystycznym koronkowym szczytem. Twarde w dotyku, słodkie. Zbieramy partiami co 5–7 dni – nie wszystkie dojrzewaja jednoczesnie."
    }
  },
  {
    "name": "Orzech włoski",
    "type": "owocowa",
    "pruning": {
      "main": { "start": "08-20", "end": "09-20" }
    },
    "instructions": [
      "TNIJ WYŁACZNIE W SIERPNIU–WRZESNIU – wiosenne ciecie powoduje silne 'krwawienie' (utrata soku).",
      "Minimalizuj zakres cięcia – orzech goi sie wolno i nie lubi duzych interwencji.",
      "Usuń suche, złamane i chore galezię na biezaco przez cały sezon.",
      "Rany po grubszych cieciach (powyzej 3 cm) smaruj mascia ogrodowa.",
      "Młode drzewa: formuj w pierwszych 5 latach, wybierajac 3–5 głównych konarow.",
      "Dorosłe drzewa: tnij tylko sanitarnie – uszkodzone, suche i chore galęzie."
    ],
    "harvest": {
      "start": "09-10",
      "end": "10-20",
      "appearance": "Zielona okrywa (łupina) peka i samoistnie odchodzi, odsłaniajac brązowa skorupe orzecha. Orzechy same zaczynaja opadac z drzewa. Zbieramy z ziemi, suszymy w przewiewnym miejscu przez 2–3 tygodnie."
    }
  },
  {
    "name": "Winorośl",
    "type": "owocowa",
    "pruning": {
      "main": { "start": "02-01", "end": "02-28" }
    },
    "instructions": [
      "TNIJ PRZED RUSZENIEM SOKOW – koniec lutego (15–28 luty); cięcie po tym terminie powoduje silne 'płakanie' rosliny.",
      "Utrzymaj trwały szkielet z głównych ramion (stare drewno), z których wyrastaja nowe latorosle.",
      "Skroc boczne latorosle (ubiegłoroczne pedy) do 2–3 oczek od nasady.",
      "Usuń wszystkie suche, chore i przerastajace pedy.",
      "Lato (maj–czerwiec): gdy nowe pedy maja 5–6 lisci, przytnij je nad 2. pakiem nad gronem (tzw. pinching).",
      "Latem usuwaj 'pazurki' (niepozadane pedy boczne) i nadmierne liscie wokol gronow dla lepszego dojrzewania."
    ],
    "harvest": {
      "start": "09-01",
      "end": "10-15",
      "appearance": "Pełne zabarwienie wlasciwe dla odmiany (zielone, żolte, czerwone lub granatowe). Jagody miekkie, słodkie – próbka smakowa to najlepsza weryfikacja. Szypułki grona zaczynaja brązowiec, nasiona sa brązowe."
    }
  },
  {
    "name": "Leszczyna",
    "type": "owocowa",
    "pruning": {
      "main": { "start": "02-01", "end": "03-15" }
    },
    "instructions": [
      "Kwitnie na starym drewnie (baziami) w lutym–marcu – tnij bezposrednio po kwitnieniu lub przed pecznieniem pąkow.",
      "Co roku usuń najstarsze pedy przy ziemi (ciemnobrązowe, spekana kora, ponad 8 lat).",
      "Regularnie i bez litosci wycinaj odrosty korzeniowe – osłabiaja krzew i moga go zdominowac.",
      "Zostaw 8–10 zdrowych pedow roznego wieku (1–8 lat) dla optymalnego owocowania.",
      "Przeswietlaj srodek krzewu – orzeszki lepiej zawiazuja sie w dobrym swietle.",
      "Stary krzew mozna odmłodzic przez silne sciecie prawie wszystkich pedow przy ziemi – odbuduje sie w 2–3 lata."
    ],
    "harvest": {
      "start": "09-01",
      "end": "10-01",
      "appearance": "Brązowe orzechy, ktore luzno wypadaja z zielonego kielicha lub same opadaja na ziemie. Łupina twarda, jadro kremowe. Zbieramy z ziemi i suszymy w suchym miejscu."
    }
  },
  {
    "name": "Pigwowiec",
    "type": "owocowa",
    "pruning": {
      "main": { "start": "05-01", "end": "06-01" }
    },
    "instructions": [
      "Kwitnie na starym i mlodym drewnie – tnij zaraz po kwitnieniu (maj–czerwiec).",
      "Usuń pedy rosnace do srodka krzewu i gałazki skrzyzowane.",
      "Co roku wytnij przy ziemi kilka najstarszych pedow, by stopniowo odmładzac krzew.",
      "UWAGA: pigwowiec ma ostre kolce – zakładaj grube rekawice skorzane.",
      "Delikatne przycinanie bocznych galazek promuje kwitnienie na krotszych rozgałezieniach (krotkopedy).",
      "Latem usuń długie, sterczace pedy zaburzajace ksztalt."
    ],
    "harvest": {
      "start": "10-01",
      "end": "11-15",
      "appearance": "Żolto-zielone, twarde i intensywnie aromatyczne owoce. Zbieramy po pierwszych przymrozkach lub tuz przed nimi. Nie nadaja sie do jedzenia na surowo – przeznaczone wyłacznie do przetworow (dzemy, galaretki, nalewki)."
    }
  },
  {
    "name": "Dereń jadalny",
    "type": "owocowa",
    "pruning": {
      "main": { "start": "03-01", "end": "03-30" }
    },
    "instructions": [
      "Kwitnie bardzo wczesnie (luty–marzec) na starym drewnie – tnij po kwitnieniu lub tuz przed pekaniem pakow.",
      "Usuń pedy krzyzujace sie i rosnace do srodka krzewu.",
      "Co roku wytnij kilka najstarszych pedow przy ziemi, by stopniowo odmładzac krzew.",
      "Przeswietl srodek krzewu dla lepszego owocowania i wentylacji.",
      "Dereń wolno rosnie – nie tnij nadmiernie, ogranicz interwencje do niezbednego minimum.",
      "Mozesz formowac jako wielopedowy krzew lub jako pien z koroną – wymaga stałego kształtowania."
    ],
    "harvest": {
      "start": "08-01",
      "end": "09-15",
      "appearance": "Ciemnoczerwone lub prawie czarne, podłuzne owoce (podobne do oliwek). Lekko miekkie w dotyku, słodko-cierpkie. Dojrzałe opadaja same lub zrywaja sie bez oporu."
    }
  },
  {
    "name": "Aronia",
    "type": "owocowa",
    "pruning": {
      "main": { "start": "03-01", "end": "03-30" }
    },
    "instructions": [
      "Owocuje najobficiej na pedach 3–6-letnich – starsze pedy sa mało produktywne.",
      "Co roku usuń najstarsze pedy (powyzej 8 lat, ciemnobrązowe) przy ziemi.",
      "Zostaw 8–12 zdrowych pedow rożnego wieku dla optymalnego plonu.",
      "Wiosna skroc pedy zbyt dlugie i rosnace poziomo lub przy ziemi.",
      "Przeswietlaj regularnie – geste krzewy aronii sa podatne na choroby grzybowe i szkodniki.",
      "Po 10–12 latach mozna odmłodzic przez silne sciecie prawie wszystkich pedow – krzew szybko sie odbuduje."
    ],
    "harvest": {
      "start": "08-20",
      "end": "09-30",
      "appearance": "Czarne, matowe jagody w gronach, pokryte delikatnym woskowym nalotem. Twarde, z mocno sciagajacym smakiem. Zbieramy całe grona. Idealne do przetworow, sokow i nalewek."
    }
  },
  {
    "name": "Klon kulisty",
    "type": "ozdobne drzewo",
    "pruning": {
      "main": { "start": "03-01", "end": "03-30" }
    },
    "instructions": [
      "Szczepiony na pieniu – korona sama tworzy naturalny ksztalt kuli, nie wymaga cięcia kształtujacego.",
      "Tnij tylko sanitarnie: usuń pedy suche, uszkodzone mrozem i rosnace pionowo w gore (wilki).",
      "Wiosna usuń pedy krzyzujace sie w srodku korony, by poprawic wentylacje.",
      "Natychmiast usun wszelkie pedy wyrastajace z pnia PONIZEJ miejsca szczepienia – to podkładka, nie odmiana ozdobna.",
      "Nie formuj kształtujaco – mocne ciecie niszczy naturalny, kulisty pokroj odmiany.",
      "Ciecie: przed ruszeniem sokow (marzec) lub po pełnym lisciu (maj–czerwiec), gdy widac suche galezki."
    ]
  },
  {
    "name": "Wierzba Hakuro-Nishiki",
    "type": "ozdobne drzewo",
    "pruning": {
      "main": { "start": "03-01", "end": "03-25" }
    },
    "instructions": [
      "Szczepiona na pieniu – wytnij NATYCHMIAST wszelkie pedy wyrastajace z pnia ponizej miejsca szczepienia.",
      "Aby uzyskac najlepszy kolor lisci (rózowo-biały), tnij MOCNO co rok wiosna.",
      "Skroc wszystkie pedy do 2–3 oczek od miejsca szczepienia (lub od zeszłorocznych czopkow).",
      "Mocne ciecie wymusza silny wzrost mlodych, intensywnie wybarwionych pedow.",
      "Stare, wieloletnie pedy maja mniej intensywny kolor – coroczne ciecie jest kluczem do atrakcyjnosci.",
      "Tnij przed ruszeniem sokow (marzec), gdy jeszcze widac układ galazek i miejsca cięcia z ubiegłego roku."
    ]
  },
  {
    "name": "Robinia akacjowa",
    "type": "ozdobne drzewo",
    "pruning": {
      "main": { "start": "03-10", "end": "04-10" }
    },
    "instructions": [
      "Ogranicz cięcie do sanitarnego minimum – rany goja sie wolno, ryzyko wnikania chorob jest wysokie.",
      "Tnij wiosna (marzec–kwiecien) przed rozwojem lisci – rany szybciej sie goja.",
      "Usuń pedy suche, złamane i chore; ciecie duze galezkie pokryj mascia ogrodowa.",
      "UWAGA: robinia ma ostre kolce – zakładaj grube rekawice i pracuj ostrożnie.",
      "Odrosty korzeniowe wycinaj regularnie – robinia silnie odrosla i moze stac sie inwazyjna.",
      "Odmiany ozdobne (np. 'Umbraculifera', 'Frisia') nie wymagaja regularnego cięcia kształtujacego."
    ]
  },
  {
    "name": "Magnolia",
    "type": "ozdobne drzewo",
    "pruning": {
      "main": { "start": "05-01", "end": "06-10" }
    },
    "instructions": [
      "Magnolia zle toleruje ciecie – tnij WYŁACZNIE bezposrednio po zakończeniu kwitnienia (maj–czerwiec).",
      "Ogranicz ciecie do sanitarnego: usuń suche, skrzyzowane i uszkodzone galezkie.",
      "Nigdy nie tnij jesienia ani zima – ryzyko przemarzania ciec i chorob grzybowych jest bardzo wysokie.",
      "Rany po grubszych cieciach (powyzej 2 cm) natychmiast smaruj mascia ogrodowa.",
      "Nie kształtuj mocno – magnolia ma naturalna, atrakcyjna sylwetke, ktora warto zachowac.",
      "Młode drzewa – przez pierwsze 5 lat nie tnij wcale, poza ewentualnym usuniéciem uszkodzeń."
    ]
  },
  {
    "name": "Bez lilak",
    "type": "ozdobna",
    "pruning": {
      "main": { "start": "05-20", "end": "06-20" }
    },
    "instructions": [
      "Kwitnie na starym drewnie – tnij ZARAZ po zakończeniu kwitnienia (maj–czerwiec), nigdy jesienia ani zima.",
      "Natychmiast usun przekwitłe kwiatostany – to kluczowe dla obfitego kwitnienia w przyszłym roku.",
      "Co roku wytnij przy ziemi 1–2 najstarsze, najgrubsze pedy, by odmładzac krzew.",
      "Usuń odrosty korzeniowe – moga osłabic szczepione odmiany lub zdominowac cały krzew.",
      "Unikaj cięcia pozniejszego niz lipiec – paki kwiatowe na przyszły rok zawiazuja sie juz latem.",
      "Stary, zaniedbany lilak odmładzaj stopniowo przez 3 lata, nie jednorazowo – nagłe 'golobrzezienie' osłabia."
    ]
  },
  {
    "name": "Oczar",
    "type": "ozdobna",
    "pruning": {
      "main": { "start": "03-01", "end": "03-30" }
    },
    "instructions": [
      "Kwitnie zimą lub wczesna wiosna (luty–marzec) – tnij zaraz po kwitnieniu.",
      "Tnij konserwatywnie – oczar wolno rosnie i wolno regeneruje sie po mocnym cieciu.",
      "Usuń pedy uszkodzone, suche i krzyzujace sie.",
      "Zachowaj naturalna, rozłozysta sylwetke krzewu – nie formuj mocno.",
      "Rany po wiekszych cieciach (powyzej 2 cm) zabezpiecz mascia ogrodowa.",
      "Co kilka lat mozesz lekko przeswietlic krzew, usuwajac kilka starszych pedow przy ziemi."
    ]
  }
]
